{
  "tasks": [
    {
      "id": "activation_checkpointing",
      "title": "Activation Checkpointing",
      "fn_name": "checkpoint_sequential",
      "difficulty": "Medium",
      "category": "注意力机制",
      "num_tests": 4,
      "capital_attr_refs": [],
      "lower_attr_refs": [],
      "has_solution_comment": false
    },
    {
      "id": "adaln_zero",
      "title": "Adaptive LayerNorm Zero (adaLN-Zero)",
      "fn_name": "adaln_zero",
      "difficulty": "Medium",
      "category": "归一化",
      "num_tests": 4,
      "capital_attr_refs": [],
      "lower_attr_refs": [],
      "has_solution_comment": true
    },
    {
      "id": "adam",
      "title": "Adam Optimizer",
      "fn_name": "MyAdam",
      "difficulty": "Medium",
      "category": "优化器与学习率",
      "num_tests": 3,
      "capital_attr_refs": [],
      "lower_attr_refs": [],
      "has_solution_comment": false
    },
    {
      "id": "alibi",
      "title": "ALiBi Attention",
      "fn_name": "alibi_attention",
      "difficulty": "Medium",
      "category": "注意力机制",
      "num_tests": 4,
      "capital_attr_refs": [],
      "lower_attr_refs": [],
      "has_solution_comment": true
    },
    {
      "id": "attention",
      "title": "Softmax Attention",
      "fn_name": "scaled_dot_product_attention",
      "difficulty": "Easy",
      "category": "注意力机制",
      "num_tests": 4,
      "capital_attr_refs": [],
      "lower_attr_refs": [],
      "has_solution_comment": false
    },
    {
      "id": "batchnorm",
      "title": "Implement BatchNorm",
      "fn_name": "my_batch_norm",
      "difficulty": "Medium",
      "category": "注意力机制",
      "num_tests": 4,
      "capital_attr_refs": [],
      "lower_attr_refs": [],
      "has_solution_comment": true
    },
    {
      "id": "beam_search",
      "title": "Beam Search Decoding",
      "fn_name": "beam_search",
      "difficulty": "Medium",
      "category": "注意力机制",
      "num_tests": 4,
      "capital_attr_refs": [],
      "lower_attr_refs": [],
      "has_solution_comment": false
    },
    {
      "id": "bpe",
      "title": "Byte-Pair Encoding (BPE)",
      "fn_name": "SimpleBPE",
      "difficulty": "Hard",
      "category": "分词",
      "num_tests": 6,
      "capital_attr_refs": [],
      "lower_attr_refs": [],
      "has_solution_comment": false
    },
    {
      "id": "causal_attention",
      "title": "Causal Self-Attention",
      "fn_name": "causal_attention",
      "difficulty": "Medium",
      "category": "注意力机制",
      "num_tests": 5,
      "capital_attr_refs": [],
      "lower_attr_refs": [],
      "has_solution_comment": false
    },
    {
      "id": "contrastive_loss",
      "title": "Contrastive Loss (InfoNCE)",
      "fn_name": "contrastive_loss",
      "difficulty": "Medium",
      "category": "损失函数",
      "num_tests": 6,
      "capital_attr_refs": [],
      "lower_attr_refs": [],
      "has_solution_comment": true
    },
    {
      "id": "conv2d",
      "title": "2D Convolution",
      "fn_name": "my_conv2d",
      "difficulty": "Medium",
      "category": "其他",
      "num_tests": 5,
      "capital_attr_refs": [],
      "lower_attr_refs": [],
      "has_solution_comment": false
    },
    {
      "id": "cosine_lr",
      "title": "Cosine LR Scheduler with Warmup",
      "fn_name": "cosine_lr_schedule",
      "difficulty": "Medium",
      "category": "注意力机制",
      "num_tests": 5,
      "capital_attr_refs": [],
      "lower_attr_refs": [],
      "has_solution_comment": false
    },
    {
      "id": "cross_attention",
      "title": "Multi-Head Cross-Attention",
      "fn_name": "MultiHeadCrossAttention",
      "difficulty": "Medium",
      "category": "注意力机制",
      "num_tests": 5,
      "capital_attr_refs": [
        "attn.W_k",
        "attn.W_q",
        "attn.W_o",
        "attn.W_v"
      ],
      "lower_attr_refs": [],
      "has_solution_comment": false
    },
    {
      "id": "cross_entropy",
      "title": "Cross-Entropy Loss",
      "fn_name": "cross_entropy_loss",
      "difficulty": "Easy",
      "category": "损失函数",
      "num_tests": 4,
      "capital_attr_refs": [],
      "lower_attr_refs": [],
      "has_solution_comment": false
    },
    {
      "id": "ddim_step",
      "title": "DDIM Sampling Step",
      "fn_name": "ddim_step",
      "difficulty": "Medium",
      "category": "扩散与流模型",
      "num_tests": 5,
      "capital_attr_refs": [],
      "lower_attr_refs": [],
      "has_solution_comment": true
    },
    {
      "id": "depthwise_conv",
      "title": "Depthwise Separable Convolution",
      "fn_name": "depthwise_separable_conv",
      "difficulty": "Medium",
      "category": "基础网络组件",
      "num_tests": 4,
      "capital_attr_refs": [],
      "lower_attr_refs": [],
      "has_solution_comment": true
    },
    {
      "id": "diff_attention",
      "title": "Differential Attention",
      "fn_name": "diff_attention",
      "difficulty": "Hard",
      "category": "注意力机制",
      "num_tests": 4,
      "capital_attr_refs": [],
      "lower_attr_refs": [],
      "has_solution_comment": false
    },
    {
      "id": "dpo_loss",
      "title": "DPO (Direct Preference Optimization) Loss",
      "fn_name": "dpo_loss",
      "difficulty": "Medium",
      "category": "损失函数",
      "num_tests": 5,
      "capital_attr_refs": [],
      "lower_attr_refs": [],
      "has_solution_comment": false
    },
    {
      "id": "dropout",
      "title": "Implement Dropout",
      "fn_name": "MyDropout",
      "difficulty": "Easy",
      "category": "注意力机制",
      "num_tests": 4,
      "capital_attr_refs": [],
      "lower_attr_refs": [],
      "has_solution_comment": false
    },
    {
      "id": "embedding",
      "title": "Embedding Layer",
      "fn_name": "MyEmbedding",
      "difficulty": "Easy",
      "category": "位置编码与嵌入",
      "num_tests": 4,
      "capital_attr_refs": [],
      "lower_attr_refs": [],
      "has_solution_comment": false
    },
    {
      "id": "flash_attention",
      "title": "Flash Attention (Tiled)",
      "fn_name": "flash_attention",
      "difficulty": "Hard",
      "category": "推理优化",
      "num_tests": 4,
      "capital_attr_refs": [],
      "lower_attr_refs": [],
      "has_solution_comment": false
    },
    {
      "id": "flow_matching",
      "title": "Flow Matching Loss",
      "fn_name": "flow_matching_loss",
      "difficulty": "Easy",
      "category": "损失函数",
      "num_tests": 6,
      "capital_attr_refs": [],
      "lower_attr_refs": [],
      "has_solution_comment": false
    },
    {
      "id": "focal_loss",
      "title": "Focal Loss",
      "fn_name": "focal_loss",
      "difficulty": "Medium",
      "category": "损失函数",
      "num_tests": 4,
      "capital_attr_refs": [],
      "lower_attr_refs": [],
      "has_solution_comment": true
    },
    {
      "id": "fsdp_step",
      "title": "FSDP Training Step",
      "fn_name": "fsdp_step",
      "difficulty": "Hard",
      "category": "高效训练",
      "num_tests": 4,
      "capital_attr_refs": [],
      "lower_attr_refs": [],
      "has_solution_comment": true
    },
    {
      "id": "gae",
      "title": "Graph Autoencoder (GAE)",
      "fn_name": "gae",
      "difficulty": "Hard",
      "category": "损失函数",
      "num_tests": 6,
      "capital_attr_refs": [],
      "lower_attr_refs": [],
      "has_solution_comment": false
    },
    {
      "id": "gat_layer",
      "title": "GAT Layer (Graph Attention)",
      "fn_name": "gat_layer",
      "difficulty": "Medium",
      "category": "注意力机制",
      "num_tests": 6,
      "capital_attr_refs": [],
      "lower_attr_refs": [],
      "has_solution_comment": false
    },
    {
      "id": "gcn_layer",
      "title": "GCN Layer (Graph Convolution)",
      "fn_name": "gcn_layer",
      "difficulty": "Easy",
      "category": "图神经网络",
      "num_tests": 6,
      "capital_attr_refs": [],
      "lower_attr_refs": [],
      "has_solution_comment": false
    },
    {
      "id": "gelu",
      "title": "GELU Activation",
      "fn_name": "my_gelu",
      "difficulty": "Easy",
      "category": "激活函数",
      "num_tests": 4,
      "capital_attr_refs": [],
      "lower_attr_refs": [],
      "has_solution_comment": false
    },
    {
      "id": "gin_layer",
      "title": "GIN Layer (Graph Isomorphism Network)",
      "fn_name": "gin_layer",
      "difficulty": "Medium",
      "category": "图神经网络",
      "num_tests": 6,
      "capital_attr_refs": [],
      "lower_attr_refs": [],
      "has_solution_comment": false
    },
    {
      "id": "gpt2_block",
      "title": "GPT-2 Transformer Block",
      "fn_name": "GPT2Block",
      "difficulty": "Hard",
      "category": "注意力机制",
      "num_tests": 5,
      "capital_attr_refs": [],
      "lower_attr_refs": [],
      "has_solution_comment": false
    },
    {
      "id": "gqa",
      "title": "Grouped Query Attention",
      "fn_name": "GroupQueryAttention",
      "difficulty": "Hard",
      "category": "注意力机制",
      "num_tests": 6,
      "capital_attr_refs": [
        "gqa.W_q",
        "gqa.W_v",
        "gqa.W_k",
        "gqa.W_o"
      ],
      "lower_attr_refs": [],
      "has_solution_comment": false
    },
    {
      "id": "gradient_accumulation",
      "title": "Gradient Accumulation",
      "fn_name": "accumulated_step",
      "difficulty": "Easy",
      "category": "优化器与学习率",
      "num_tests": 3,
      "capital_attr_refs": [],
      "lower_attr_refs": [],
      "has_solution_comment": false
    },
    {
      "id": "gradient_clipping",
      "title": "Gradient Norm Clipping",
      "fn_name": "clip_grad_norm",
      "difficulty": "Easy",
      "category": "其他",
      "num_tests": 4,
      "capital_attr_refs": [],
      "lower_attr_refs": [],
      "has_solution_comment": false
    },
    {
      "id": "graph_readout",
      "title": "Graph Readout (Graph-Level Pooling)",
      "fn_name": "graph_readout",
      "difficulty": "Easy",
      "category": "图神经网络",
      "num_tests": 6,
      "capital_attr_refs": [],
      "lower_attr_refs": [],
      "has_solution_comment": false
    },
    {
      "id": "graphsage_layer",
      "title": "GraphSAGE Layer",
      "fn_name": "graphsage_layer",
      "difficulty": "Hard",
      "category": "图神经网络",
      "num_tests": 8,
      "capital_attr_refs": [],
      "lower_attr_refs": [],
      "has_solution_comment": false
    },
    {
      "id": "grpo_loss",
      "title": "GRPO (Group Relative Policy Optimization) Loss",
      "fn_name": "grpo_loss",
      "difficulty": "Hard",
      "category": "损失函数",
      "num_tests": 4,
      "capital_attr_refs": [],
      "lower_attr_refs": [],
      "has_solution_comment": true
    },
    {
      "id": "int8_quantization",
      "title": "INT8 Quantized Linear",
      "fn_name": "Int8Linear",
      "difficulty": "Hard",
      "category": "量化",
      "num_tests": 5,
      "capital_attr_refs": [],
      "lower_attr_refs": [],
      "has_solution_comment": false
    },
    {
      "id": "kv_cache",
      "title": "KV Cache Attention",
      "fn_name": "KVCacheAttention",
      "difficulty": "Hard",
      "category": "推理优化",
      "num_tests": 5,
      "capital_attr_refs": [],
      "lower_attr_refs": [],
      "has_solution_comment": true
    },
    {
      "id": "label_smoothing",
      "title": "Label Smoothing Loss",
      "fn_name": "label_smoothing",
      "difficulty": "Easy",
      "category": "损失函数",
      "num_tests": 5,
      "capital_attr_refs": [],
      "lower_attr_refs": [],
      "has_solution_comment": false
    },
    {
      "id": "layernorm",
      "title": "Implement LayerNorm",
      "fn_name": "my_layer_norm",
      "difficulty": "Medium",
      "category": "归一化",
      "num_tests": 3,
      "capital_attr_refs": [],
      "lower_attr_refs": [],
      "has_solution_comment": false
    },
    {
      "id": "linear",
      "title": "Simple Linear Layer",
      "fn_name": "SimpleLinear",
      "difficulty": "Medium",
      "category": "基础网络组件",
      "num_tests": 3,
      "capital_attr_refs": [],
      "lower_attr_refs": [],
      "has_solution_comment": false
    },
    {
      "id": "linear_attention",
      "title": "Linear Self-Attention",
      "fn_name": "linear_attention",
      "difficulty": "Hard",
      "category": "注意力机制",
      "num_tests": 5,
      "capital_attr_refs": [],
      "lower_attr_refs": [],
      "has_solution_comment": true
    },
    {
      "id": "linear_regression",
      "title": "Linear Regression",
      "fn_name": "LinearRegression",
      "difficulty": "Medium",
      "category": "基础网络组件",
      "num_tests": 6,
      "capital_attr_refs": [],
      "lower_attr_refs": [],
      "has_solution_comment": true
    },
    {
      "id": "link_prediction",
      "title": "Link Prediction",
      "fn_name": "link_prediction",
      "difficulty": "Hard",
      "category": "图神经网络",
      "num_tests": 6,
      "capital_attr_refs": [],
      "lower_attr_refs": [],
      "has_solution_comment": false
    },
    {
      "id": "lora",
      "title": "LoRA (Low-Rank Adaptation)",
      "fn_name": "LoRALinear",
      "difficulty": "Medium",
      "category": "参数高效微调",
      "num_tests": 5,
      "capital_attr_refs": [],
      "lower_attr_refs": [],
      "has_solution_comment": false
    },
    {
      "id": "mamba_ssm",
      "title": "Mamba SSM Step",
      "fn_name": "mamba_ssm_step",
      "difficulty": "Hard",
      "category": "状态空间模型",
      "num_tests": 5,
      "capital_attr_refs": [],
      "lower_attr_refs": [],
      "has_solution_comment": true
    },
    {
      "id": "max_pool2d",
      "title": "Max Pooling 2D",
      "fn_name": "max_pool2d",
      "difficulty": "Easy",
      "category": "基础网络组件",
      "num_tests": 4,
      "capital_attr_refs": [],
      "lower_attr_refs": [],
      "has_solution_comment": true
    },
    {
      "id": "mcts_search",
      "title": "MCTS for Reasoning",
      "fn_name": "mcts_step",
      "difficulty": "Hard",
      "category": "采样与解码",
      "num_tests": 5,
      "capital_attr_refs": [],
      "lower_attr_refs": [],
      "has_solution_comment": true
    },
    {
      "id": "mha",
      "title": "Multi-Head Attention",
      "fn_name": "MultiHeadAttention",
      "difficulty": "Hard",
      "category": "注意力机制",
      "num_tests": 7,
      "capital_attr_refs": [
        "mha.W_q",
        "mha.W_o",
        "mha.W_v",
        "mha.W_k"
      ],
      "lower_attr_refs": [],
      "has_solution_comment": false
    },
    {
      "id": "mixed_precision",
      "title": "Mixed Precision Training Step",
      "fn_name": "mixed_precision_step",
      "difficulty": "Medium",
      "category": "高效训练",
      "num_tests": 5,
      "capital_attr_refs": [],
      "lower_attr_refs": [],
      "has_solution_comment": true
    },
    {
      "id": "mla",
      "title": "Multi-Head Latent Attention (MLA)",
      "fn_name": "mla_attention",
      "difficulty": "Hard",
      "category": "注意力机制",
      "num_tests": 5,
      "capital_attr_refs": [],
      "lower_attr_refs": [],
      "has_solution_comment": true
    },
    {
      "id": "mlp",
      "title": "SwiGLU MLP",
      "fn_name": "SwiGLUMLP",
      "difficulty": "Medium",
      "category": "激活函数",
      "num_tests": 5,
      "capital_attr_refs": [],
      "lower_attr_refs": [],
      "has_solution_comment": false
    },
    {
      "id": "moe",
      "title": "Mixture of Experts (MoE)",
      "fn_name": "MixtureOfExperts",
      "difficulty": "Hard",
      "category": "混合专家模型",
      "num_tests": 5,
      "capital_attr_refs": [],
      "lower_attr_refs": [],
      "has_solution_comment": false
    },
    {
      "id": "moe_load_balance",
      "title": "MoE Load Balancing Loss",
      "fn_name": "moe_load_balance_loss",
      "difficulty": "Medium",
      "category": "损失函数",
      "num_tests": 4,
      "capital_attr_refs": [],
      "lower_attr_refs": [],
      "has_solution_comment": true
    },
    {
      "id": "mpnn_layer",
      "title": "MPNN Layer (Message Passing)",
      "fn_name": "mpnn_layer",
      "difficulty": "Medium",
      "category": "图神经网络",
      "num_tests": 6,
      "capital_attr_refs": [],
      "lower_attr_refs": [],
      "has_solution_comment": false
    },
    {
      "id": "multi_token_prediction",
      "title": "Multi-Token Prediction Loss",
      "fn_name": "multi_token_prediction_loss",
      "difficulty": "Medium",
      "category": "损失函数",
      "num_tests": 4,
      "capital_attr_refs": [],
      "lower_attr_refs": [],
      "has_solution_comment": true
    },
    {
      "id": "noise_schedule",
      "title": "Diffusion Noise Schedules",
      "fn_name": "noise_schedule",
      "difficulty": "Easy",
      "category": "扩散与流模型",
      "num_tests": 7,
      "capital_attr_refs": [],
      "lower_attr_refs": [],
      "has_solution_comment": false
    },
    {
      "id": "ntk_rope",
      "title": "NTK-aware RoPE Scaling",
      "fn_name": "ntk_rope",
      "difficulty": "Easy",
      "category": "注意力机制",
      "num_tests": 5,
      "capital_attr_refs": [],
      "lower_attr_refs": [],
      "has_solution_comment": false
    },
    {
      "id": "paged_attention",
      "title": "Paged Attention",
      "fn_name": "paged_attention",
      "difficulty": "Hard",
      "category": "推理优化",
      "num_tests": 4,
      "capital_attr_refs": [],
      "lower_attr_refs": [],
      "has_solution_comment": true
    },
    {
      "id": "ppo_loss",
      "title": "PPO (Proximal Policy Optimization) Clipped Loss",
      "fn_name": "ppo_loss",
      "difficulty": "Medium",
      "category": "注意力机制",
      "num_tests": 3,
      "capital_attr_refs": [],
      "lower_attr_refs": [],
      "has_solution_comment": true
    },
    {
      "id": "qlora",
      "title": "QLoRA",
      "fn_name": "QLoRALinear",
      "difficulty": "Hard",
      "category": "量化",
      "num_tests": 5,
      "capital_attr_refs": [],
      "lower_attr_refs": [],
      "has_solution_comment": false
    },
    {
      "id": "relu",
      "title": "Implement ReLU",
      "fn_name": "relu",
      "difficulty": "Easy",
      "category": "激活函数",
      "num_tests": 4,
      "capital_attr_refs": [],
      "lower_attr_refs": [],
      "has_solution_comment": false
    },
    {
      "id": "reward_model",
      "title": "Bradley-Terry Reward Model Loss",
      "fn_name": "reward_model_loss",
      "difficulty": "Medium",
      "category": "损失函数",
      "num_tests": 5,
      "capital_attr_refs": [],
      "lower_attr_refs": [],
      "has_solution_comment": true
    },
    {
      "id": "ring_attention",
      "title": "Ring Attention",
      "fn_name": "ring_attention",
      "difficulty": "Hard",
      "category": "推理优化",
      "num_tests": 4,
      "capital_attr_refs": [],
      "lower_attr_refs": [],
      "has_solution_comment": true
    },
    {
      "id": "rmsnorm",
      "title": "Implement RMSNorm",
      "fn_name": "rms_norm",
      "difficulty": "Medium",
      "category": "归一化",
      "num_tests": 5,
      "capital_attr_refs": [],
      "lower_attr_refs": [],
      "has_solution_comment": false
    },
    {
      "id": "rope",
      "title": "Rotary Position Embedding (RoPE)",
      "fn_name": "apply_rope",
      "difficulty": "Medium",
      "category": "注意力机制",
      "num_tests": 5,
      "capital_attr_refs": [],
      "lower_attr_refs": [],
      "has_solution_comment": false
    },
    {
      "id": "sinusoidal_pe",
      "title": "Sinusoidal Position Encoding",
      "fn_name": "sinusoidal_pe",
      "difficulty": "Easy",
      "category": "注意力机制",
      "num_tests": 4,
      "capital_attr_refs": [],
      "lower_attr_refs": [],
      "has_solution_comment": false
    },
    {
      "id": "sliding_window",
      "title": "Sliding Window Attention",
      "fn_name": "sliding_window_attention",
      "difficulty": "Medium",
      "category": "注意力机制",
      "num_tests": 5,
      "capital_attr_refs": [],
      "lower_attr_refs": [],
      "has_solution_comment": false
    },
    {
      "id": "softmax",
      "title": "Implement Softmax",
      "fn_name": "my_softmax",
      "difficulty": "Easy",
      "category": "注意力机制",
      "num_tests": 4,
      "capital_attr_refs": [],
      "lower_attr_refs": [],
      "has_solution_comment": false
    },
    {
      "id": "speculative_decoding",
      "title": "Speculative Decoding",
      "fn_name": "speculative_decode",
      "difficulty": "Hard",
      "category": "推理优化",
      "num_tests": 4,
      "capital_attr_refs": [],
      "lower_attr_refs": [],
      "has_solution_comment": false
    },
    {
      "id": "swiglu",
      "title": "SwiGLU Activation",
      "fn_name": "swiglu",
      "difficulty": "Medium",
      "category": "激活函数",
      "num_tests": 3,
      "capital_attr_refs": [],
      "lower_attr_refs": [],
      "has_solution_comment": false
    },
    {
      "id": "tensor_parallel",
      "title": "Tensor Parallel MLP",
      "fn_name": "TensorParallelMLP",
      "difficulty": "Hard",
      "category": "高效训练",
      "num_tests": 4,
      "capital_attr_refs": [],
      "lower_attr_refs": [],
      "has_solution_comment": true
    },
    {
      "id": "topk_sampling",
      "title": "Top-k / Top-p Sampling",
      "fn_name": "sample_top_k_top_p",
      "difficulty": "Medium",
      "category": "采样与解码",
      "num_tests": 5,
      "capital_attr_refs": [],
      "lower_attr_refs": [],
      "has_solution_comment": false
    },
    {
      "id": "vit_block",
      "title": "ViT Transformer Block",
      "fn_name": "ViTBlock",
      "difficulty": "Hard",
      "category": "注意力机制",
      "num_tests": 6,
      "capital_attr_refs": [],
      "lower_attr_refs": [],
      "has_solution_comment": false
    },
    {
      "id": "vit_patch",
      "title": "ViT Patch Embedding",
      "fn_name": "PatchEmbedding",
      "difficulty": "Medium",
      "category": "位置编码与嵌入",
      "num_tests": 5,
      "capital_attr_refs": [],
      "lower_attr_refs": [],
      "has_solution_comment": false
    },
    {
      "id": "weight_init",
      "title": "Kaiming Initialization",
      "fn_name": "kaiming_init",
      "difficulty": "Easy",
      "category": "其他",
      "num_tests": 4,
      "capital_attr_refs": [],
      "lower_attr_refs": [],
      "has_solution_comment": false
    }
  ],
  "attr_issues": [
    {
      "id": "cross_attention",
      "attrs": [
        "attn.W_k",
        "attn.W_q",
        "attn.W_o",
        "attn.W_v"
      ]
    },
    {
      "id": "gqa",
      "attrs": [
        "gqa.W_q",
        "gqa.W_v",
        "gqa.W_k",
        "gqa.W_o"
      ]
    },
    {
      "id": "mha",
      "attrs": [
        "mha.W_q",
        "mha.W_o",
        "mha.W_v",
        "mha.W_k"
      ]
    }
  ],
  "no_comment": [
    "activation_checkpointing",
    "adam",
    "attention",
    "beam_search",
    "bpe",
    "causal_attention",
    "conv2d",
    "cosine_lr",
    "cross_attention",
    "cross_entropy",
    "diff_attention",
    "dpo_loss",
    "dropout",
    "embedding",
    "flash_attention",
    "flow_matching",
    "gae",
    "gat_layer",
    "gcn_layer",
    "gelu",
    "gin_layer",
    "gpt2_block",
    "gqa",
    "gradient_accumulation",
    "gradient_clipping",
    "graph_readout",
    "graphsage_layer",
    "int8_quantization",
    "label_smoothing",
    "layernorm",
    "linear",
    "link_prediction",
    "lora",
    "mha",
    "mlp",
    "moe",
    "mpnn_layer",
    "noise_schedule",
    "ntk_rope",
    "qlora",
    "relu",
    "rmsnorm",
    "rope",
    "sinusoidal_pe",
    "sliding_window",
    "softmax",
    "speculative_decoding",
    "swiglu",
    "topk_sampling",
    "vit_block",
    "vit_patch",
    "weight_init"
  ]
}